sysfacts/__init__.py
sysfacts/api.py
sysfacts/cli.py
sysfacts-0.2.0.dist-info/entry_points.txt
sysfacts-0.2.0.dist-info/LICENSE
sysfacts-0.2.0.dist-info/WHEEL
sysfacts-0.2.0.dist-info/METADATA
sysfacts-0.2.0.dist-info/RECORD
