Metadata-Version: 2.1
Name: sysfacts
Version: 0.2.0
Summary: Collect system information
Home-page: https://github.com/pmav99/sysfacts
License: MIT
Keywords: system,information,facts,collect,collection,gather
Author: Panos Mavrogiorgos
Author-email: pmav99@gmail.com
Requires-Python: >=3.6,<4.0
Classifier: License :: OSI Approved :: MIT License
Classifier: Programming Language :: Python :: 3
Classifier: Programming Language :: Python :: 3.6
Classifier: Programming Language :: Python :: 3.7
Classifier: Topic :: Software Development :: Libraries :: Python Modules
Requires-Dist: click (>=7.0,<8.0)
Requires-Dist: distro (>=1.3,<2.0)
Requires-Dist: pendulum (>=2.0,<3.0)
Requires-Dist: psutil (>=5.4,<6.0)
Requires-Dist: py-cpuinfo (>=4.0,<5.0)
Requires-Dist: pygments (>=2.3,<3.0)
Requires-Dist: ruamel.yaml (>=0.15.86,<0.16.0)
Project-URL: Documentation, https://github.com/pmav99/sysfacts
Project-URL: Repository, https://github.com/pmav99/sysfacts
